setup.py
datadaemon/__init__.py
datadaemon/datadaemon.py
datadaemon/mainframe.py
datadaemon/shepherd.py
datadaemon.egg-info/PKG-INFO
datadaemon.egg-info/SOURCES.txt
datadaemon.egg-info/dependency_links.txt
datadaemon.egg-info/entry_points.txt
datadaemon.egg-info/requires.txt
datadaemon.egg-info/top_level.txt
datadaemon/base/__init__.py
datadaemon/base/basegrabber.py
datadaemon/base/ccxtgrabber.py
datadaemon/base/rgrabber.py
datadaemon/utilities/__init__.py
datadaemon/utilities/exception.py
datadaemon/utilities/glob.py
datadaemon/utilities/log.py
datadaemon/utilities/singleton.py