Metadata-Version: 1.1
Name: datadaemon
Version: 1.1.2
Summary: An cryptocurrency kline data collecting tool.
Home-page: UNKNOWN
Author: Ghost
Author-email: UNKNOWN
License: MIT
Keywords: cryptocurrency,data collecting
Platform: UNKNOWN
Classifier: Development Status :: 4 - Beta
Classifier: Intended Audience :: Developers
Classifier: Intended Audience :: Financial and Insurance Industry
Classifier: Intended Audience :: Information Technology
Classifier: Topic :: Software Development :: Build Tools
Classifier: Topic :: Office/Business :: Financial :: Investment
Classifier: License :: OSI Approved :: MIT License
Classifier: Programming Language :: Python :: 3.6
Classifier: Operating System :: OS Independent
Classifier: Environment :: Console
